threatingestor/__init__.py
threatingestor/artifacts.py
threatingestor/config.py
threatingestor/exceptions.py
threatingestor/state.py
threatingestor/whitelist.py
threatingestor/extras/__init__.py
threatingestor/extras/fswatcher.py
threatingestor/extras/pasteprocessor.py
threatingestor/extras/queueworker.py
threatingestor/extras/webapp.py
threatingestor/operators/__init__.py
threatingestor/operators/abstract_json.py
threatingestor/operators/beanstalk.py
threatingestor/operators/csv.py
threatingestor/operators/misp.py
threatingestor/operators/mysql.py
threatingestor/operators/sqlite.py
threatingestor/operators/sqs.py
threatingestor/operators/threatkb.py
threatingestor/sources/__init__.py
threatingestor/sources/abstract_json.py
threatingestor/sources/beanstalk.py
threatingestor/sources/git.py
threatingestor/sources/github.py
threatingestor/sources/github_gist.py
threatingestor/sources/image.py
threatingestor/sources/rss.py
threatingestor/sources/sitemap.py
threatingestor/sources/sqs.py
threatingestor/sources/twitter.py
threatingestor/sources/virustotal.py
threatingestor/sources/web.py
threatingestor-1.4.0.dist-info/LICENSE
threatingestor-1.4.0.dist-info/METADATA
threatingestor-1.4.0.dist-info/WHEEL
threatingestor-1.4.0.dist-info/entry_points.txt
threatingestor-1.4.0.dist-info/top_level.txt
threatingestor-1.4.0.dist-info/RECORD
