Metadata-Version: 2.1
Name: threatingestor
Version: 1.4.0
Summary: Extract and aggregate IOCs from threat feeds.
Home-page: https://github.com/InQuest/ThreatIngestor
Author: InQuest Labs
Author-email: labs@inquest.net
License: GPL
Classifier: Intended Audience :: Developers
Classifier: Intended Audience :: Information Technology
Classifier: Intended Audience :: System Administrators
Classifier: License :: OSI Approved :: GNU General Public License v2 (GPLv2)
Classifier: Operating System :: OS Independent
Classifier: Programming Language :: Python :: 3.6
Classifier: Programming Language :: Python :: 3.7
Classifier: Programming Language :: Python :: 3 :: Only
Classifier: Topic :: Security
Classifier: Topic :: Internet
License-File: LICENSE
Requires-Dist: beautifulsoup4 >=4.4.1
Requires-Dist: ipaddress >=1.0.18
Requires-Dist: iocextract >=1.12.1
Requires-Dist: PyYAML >=3.13
Requires-Dist: jsonpath-rw >=1.4.0
Requires-Dist: sgmllib3k
Requires-Dist: loguru
Requires-Dist: statsd
Requires-Dist: requests
Requires-Dist: pyshorteners
Requires-Dist: twitter >=2.0a2
Provides-Extra: all
Requires-Dist: httpretty ; extra == 'all'
Requires-Dist: responses ; extra == 'all'
Requires-Dist: mock ; extra == 'all'
Requires-Dist: boto3 ; extra == 'all'
Requires-Dist: Nose ; extra == 'all'
Requires-Dist: sphinx ; extra == 'all'
Requires-Dist: Pygments ; extra == 'all'
Requires-Dist: collective.checkdocs ; extra == 'all'
Requires-Dist: coverage ; extra == 'all'
Requires-Dist: hug ; extra == 'all'
Requires-Dist: pymisp ; extra == 'all'
Requires-Dist: greenstalk ==1.0.1 ; extra == 'all'
Requires-Dist: watchdog ; extra == 'all'
Requires-Dist: twitter >=1.17.1 ; extra == 'all'
Requires-Dist: feedparser >=5.2.1 ; extra == 'all'
Requires-Dist: threatkb ; extra == 'all'
Requires-Dist: pymysql ; extra == 'all'
Requires-Dist: pyshorteners ; extra == 'all'
Provides-Extra: beanstalk
Requires-Dist: greenstalk ; extra == 'beanstalk'
Provides-Extra: extras
Requires-Dist: hug ; extra == 'extras'
Requires-Dist: boto3 ; extra == 'extras'
Requires-Dist: greenstalk ; extra == 'extras'
Requires-Dist: watchdog ; extra == 'extras'
Provides-Extra: misp
Requires-Dist: PyMISP ; extra == 'misp'
Provides-Extra: mysql
Requires-Dist: pymysql ; extra == 'mysql'
Provides-Extra: rss
Requires-Dist: feedparser ; extra == 'rss'
Provides-Extra: sqs
Requires-Dist: boto3 ; extra == 'sqs'
Provides-Extra: threatkb
Requires-Dist: threatkb ; extra == 'threatkb'
Provides-Extra: twitter
Requires-Dist: twitter ; extra == 'twitter'
